packaging-classifiers/__init__.py
packaging-classifiers/models.py
packaging_classifiers/__init__.py
packaging_classifiers/models.py
packaging_classifiers-1.0.0rc5.dist-info/METADATA
packaging_classifiers-1.0.0rc5.dist-info/WHEEL
packaging_classifiers-1.0.0rc5.dist-info/top_level.txt
packaging_classifiers-1.0.0rc5.dist-info/RECORD
