Metadata-Version: 2.1
Name: packaging-classifiers
Version: 1.0.0rc5
Summary: Cannonical source for classifiers on PyPI (pypi.org).
Home-page: https://github.com/pypa/packaging-classifiers
Author: Dustin Ingram
Author-email: di@python.org
License: UNKNOWN
Keywords: classifiers
Platform: UNKNOWN
